<?xml version="1.0" encoding="UTF-8" standalone="yes"?>
<lionengine:featurable xmlns:lionengine="http://lionengine.b3dgs.com/xsd/9" xmlns:xsi="http://www.w3.org/2001/XMLSchema-instance" xsi:schemaLocation="http://lionengine.b3dgs.com/xsd/9 http://lionengine.b3dgs.com/xsd/9/featurable.xsd">
    <lionengine:class>com.b3dgs.lionengine.helper.EntityHelper</lionengine:class>
    <lionengine:features>
        <lionengine:feature>com.b3dgs.lionheart.object.EntityModel</lionengine:feature>
        <lionengine:feature>com.b3dgs.lionheart.object.feature.Stats</lionengine:feature>
        <lionengine:feature>com.b3dgs.lionheart.object.feature.Glue</lionengine:feature>
        <lionengine:feature>com.b3dgs.lionheart.object.feature.Hurtable</lionengine:feature>
        <lionengine:feature>com.b3dgs.lionheart.object.feature.Underwater</lionengine:feature>
        <lionengine:feature>com.b3dgs.lionheart.object.feature.Floater</lionengine:feature>
    </lionengine:features>
    <lionengine:surface image="FloaterCube.png" icon="FloaterCube_ico.png"/>
    <lionengine:frames horizontal="2" vertical="1"/>
    <lionengine:size width="32" height="32"/>
    <lionengine:origin>CENTER_BOTTOM</lionengine:origin>
    <lionengine:animations>
        <lionengine:animation name="idle" start="1" end="1" speed="1.0" reversed="false" repeat="false"/>
        <lionengine:animation name="fall" start="1" end="1" speed="1.0" reversed="false" repeat="false"/>
        <lionengine:animation name="land" start="1" end="1" speed="1.0" reversed="false" repeat="false"/>
        <lionengine:animation name="hurt" start="1" end="1" speed="1.0" reversed="false" repeat="false"/>
    </lionengine:animations>
    <lionengine:collisions>
        <lionengine:collision name="ground" offsetX="0" offsetY="32" width="28" height="1" mirror="false"/>
        <lionengine:collision name="body" offsetX="0" offsetY="0" width="28" height="33" mirror="false"/>
    </lionengine:collisions>
    <lionengine:categories>
        <lionengine:category name="leg" axis="Y" x="0" y="0">
            <lionengine:group>ground15</lionengine:group>
        </lionengine:category>
    </lionengine:categories>
    <lionengine:state>com.b3dgs.lionheart.object.state.StateIdle</lionengine:state>
    <lionengine:rasterable extern="true"/>
    <lionengine:layerable layerRefresh="2" layerDisplay="8"/>
    <lionengine:body gravity="2.0" gravityMax="7.0"/>
    <lionengine:collidable group="2" accepted="1"/>
    <stats health="-1" persist="true"/>
    <hurtable frame="2"/>
    <alwaysUpdate>true</alwaysUpdate>
    <floater speedUp="0.4" speedDown="0.2" max="5" hit="true"/>
</lionengine:featurable>